ds_cache_cleaner/__init__.py
ds_cache_cleaner/__main__.py
ds_cache_cleaner/cli.py
ds_cache_cleaner/metadata.py
ds_cache_cleaner/utils.py
ds_cache_cleaner/version.py
ds_cache_cleaner/caches/__init__.py
ds_cache_cleaner/caches/base.py
ds_cache_cleaner/caches/datamaestro.py
ds_cache_cleaner/caches/datasets.py
ds_cache_cleaner/caches/huggingface.py
ds_cache_cleaner/caches/ir_datasets.py
ds_cache_cleaner/caches/transformers.py
ds_cache_cleaner/tui/__init__.py
ds_cache_cleaner/tui/app.py
ds_cache_cleaner-0.4.0.dist-info/METADATA
ds_cache_cleaner-0.4.0.dist-info/WHEEL
ds_cache_cleaner-0.4.0.dist-info/entry_points.txt
ds_cache_cleaner-0.4.0.dist-info/licenses/LICENSE
ds_cache_cleaner-0.4.0.dist-info/RECORD
