Metadata-Version: 2.4
Name: ds-cache-cleaner
Version: 0.4.0
Summary: Clean up cached data from ML/data science libraries
Project-URL: Documentation, https://github.com/bpiwowar/ds-cache-cleaner#readme
Project-URL: Issues, https://github.com/bpiwowar/ds-cache-cleaner/issues
Project-URL: Source, https://github.com/bpiwowar/ds-cache-cleaner
Author-email: Your Name <you@example.com>
License-Expression: MIT
License-File: LICENSE
Keywords: cache,cleanup,data-science,huggingface,machine-learning
Classifier: Development Status :: 3 - Alpha
Classifier: Environment :: Console
Classifier: Intended Audience :: Developers
Classifier: Intended Audience :: Science/Research
Classifier: License :: OSI Approved :: MIT License
Classifier: Programming Language :: Python :: 3
Classifier: Programming Language :: Python :: 3.10
Classifier: Programming Language :: Python :: 3.11
Classifier: Programming Language :: Python :: 3.12
Classifier: Topic :: Scientific/Engineering :: Artificial Intelligence
Classifier: Topic :: System :: Filesystems
Requires-Python: >=3.10
Requires-Dist: click>=8.0
Requires-Dist: pydantic>=2.0
Requires-Dist: rich>=13.0
Requires-Dist: textual>=0.40
Provides-Extra: dev
Requires-Dist: mypy>=1.0; extra == 'dev'
Requires-Dist: pytest-cov>=4.0; extra == 'dev'
Requires-Dist: pytest-timeout>=2.0; extra == 'dev'
Requires-Dist: pytest>=8.0; extra == 'dev'
Requires-Dist: ruff>=0.1; extra == 'dev'
Requires-Dist: textual-dev>=1.0; extra == 'dev'
